Metadata-Version: 1.1
Name: percstat
Version: 0.0.0a5
Summary: korean high school 3rd grade math with python3!
Home-page: UNKNOWN
Author: jeong seojin
Author-email: seojin04230423@gmail.com
License: BSD
Platform: UNKNOWN
Classifier: Programming Language :: Python :: 3
Classifier: License :: OSI Approved :: BSD License
Classifier: Operating System :: OS Independent
